gym_deepmindlab/__init__.py
gym_deepmindlab/env.py
gym_deepmindlab-0.1.2.dist-info/LICENSE
gym_deepmindlab-0.1.2.dist-info/METADATA
gym_deepmindlab-0.1.2.dist-info/WHEEL
gym_deepmindlab-0.1.2.dist-info/top_level.txt
gym_deepmindlab-0.1.2.dist-info/RECORD
