Metadata-Version: 2.1
Name: gym-deepmindlab
Version: 0.1.2
Summary: Gym interface to deepmind_lab environment
Home-page: https://github.com/jkulhanek/gym-deepmindlab-env
Author: Jonáš Kulhánek
Author-email: jonas.kulhanek@live.com
License: UNKNOWN
Platform: UNKNOWN
Classifier: Programming Language :: Python :: 3
Classifier: License :: OSI Approved :: MIT License
Classifier: Operating System :: OS Independent
